geohashing/tests.py
geohashing/views.py
geohashing/urls.py
geohashing/models.py
geohashing/__init__.py
geohashing/admin.py
geohashing/serializers.py
geohashing/utils.py
geohashing/management/__init__.py
geohashing/management/commands/get_historical_djia.py
geohashing/management/commands/__init__.py
geohashing/migrations/0001_initial.py
geohashing/migrations/__init__.py
django_geohashing-0.2.1.dist-info/pbr.json
django_geohashing-0.2.1.dist-info/METADATA
django_geohashing-0.2.1.dist-info/WHEEL
django_geohashing-0.2.1.dist-info/DESCRIPTION.rst
django_geohashing-0.2.1.dist-info/RECORD
django_geohashing-0.2.1.dist-info/top_level.txt
django_geohashing-0.2.1.dist-info/metadata.json
