Metadata-Version: 2.0
Name: django-geohashing
Version: 0.2.1
Summary: Django app for working with XKCD geohashing data
Home-page: UNKNOWN
Author: Chuck Bassett
Author-email: iamchuckb@gmail.com
License: MIT License
Keywords: geohashing xkcd django
Platform: UNKNOWN
Classifier: Development Status :: 3 - Alpha
Classifier: Environment :: Web Environment
Classifier: Framework :: Django
Classifier: Intended Audience :: Developers
Classifier: License :: OSI Approved :: MIT License
Classifier: Operating System :: OS Independent
Classifier: Programming Language :: Python
Classifier: Topic :: Internet :: WWW/HTTP
Classifier: Topic :: Internet :: WWW/HTTP :: Dynamic Content
Requires-Dist: django
Requires-Dist: requests
Requires-Dist: djangorestframework
